liberty/__init__.py
liberty/airflow/dags/__init__.py
liberty/airflow/dags/airflow/__init__.py
liberty/airflow/dags/airflow/purge.py
liberty/airflow/dags/airflow/sync.py
liberty/airflow/dags/database/__init__.py
liberty/airflow/dags/database/backup.py
liberty/airflow/dags/database/purge.py
liberty/airflow/plugins/__init__.py
liberty/airflow/plugins/airflow/__init__.py
liberty/airflow/plugins/database/__init__.py
liberty/airflow/plugins/database/oracle/__init__.py
liberty/airflow/plugins/database/oracle/db_meta.py
liberty/airflow/plugins/database/postgres/__init__.py
liberty/airflow/plugins/database/postgres/db_backup.py
liberty/airflow/plugins/database/postgres/db_merge.py
liberty/airflow/plugins/database/postgres/db_meta.py
liberty/airflow/plugins/database/utils/__init__.py
liberty/airflow/plugins/database/utils/db_copy.py
liberty/airflow/plugins/database/utils/db_meta.py
liberty/airflow/plugins/git/__init__.py
liberty/airflow/plugins/git/utils.py
liberty_airflow_plugins-1.0.9.dist-info/licenses/LICENSE.md
liberty_airflow_plugins-1.0.9.dist-info/METADATA
liberty_airflow_plugins-1.0.9.dist-info/WHEEL
liberty_airflow_plugins-1.0.9.dist-info/top_level.txt
liberty_airflow_plugins-1.0.9.dist-info/RECORD
