Metadata-Version: 2.4
Name: liberty-airflow-plugins
Version: 1.0.9
Summary: Plugins for Liberty Airflow
Home-page: https://nomana-it.fr
Author: Franck Blettner
Author-email: franck.blettner@nomana-it.fr 
Classifier: Programming Language :: Python :: 3
Classifier: Operating System :: OS Independent
Requires-Python: >=3.12
License-File: LICENSE.md
Requires-Dist: apache-airflow==3.0.1
Requires-Dist: cryptography==43.0.0
Requires-Dist: ldap3==2.9.1
Requires-Dist: oracledb==2.4.1
Requires-Dist: pendulum==3.0.0
Requires-Dist: pyspark==3.5.3
Requires-Dist: setuptools==75.2.0
Requires-Dist: build
Requires-Dist: apache-airflow-providers-postgres
Dynamic: author
Dynamic: author-email
Dynamic: classifier
Dynamic: description
Dynamic: description-content-type
Dynamic: home-page
Dynamic: license-file
Dynamic: requires-dist
Dynamic: requires-python
Dynamic: summary
